siepicfab_ebeam_zep/DFT.xml
siepicfab_ebeam_zep/SiEPICfab_EBeam_ZEP.lyp
siepicfab_ebeam_zep/SiEPICfab_EBeam_ZEP.lyt
siepicfab_ebeam_zep/Verification.xml
siepicfab_ebeam_zep/WAVEGUIDES.xml
siepicfab_ebeam_zep/WAVEGUIDES_legacy.xml
siepicfab_ebeam_zep/WAVEGUIDES_lukasc.xml
siepicfab_ebeam_zep/__init__.py
siepicfab_ebeam_zep/CML/SiEPICfab_EBeam_ZEP/source_data/wg_integral_source_1310/wg_strip_lookup_table.xml
siepicfab_ebeam_zep/drc/ELEC463-2021.lydrc
siepicfab_ebeam_zep/drc/SiEPICfab_EBeam_ZEP.lydrc
siepicfab_ebeam_zep/pymacros/SiEPICfab_ZEP_export.py
siepicfab_ebeam_zep/pymacros/ZEP_Lib_PCellTests.py
siepicfab_ebeam_zep/pymacros/__init__.py
siepicfab_ebeam_zep/pymacros/custom_exceptions.py
siepicfab_ebeam_zep/pymacros/extract_EBL_regions_example.gds
siepicfab_ebeam_zep/pymacros/SiEPICfab_EBeam_ZEP_beta_fixed/LASER_1270_DFB.gds
siepicfab_ebeam_zep/pymacros/SiEPICfab_EBeam_ZEP_beta_fixed/LASER_1310_DFB.gds
siepicfab_ebeam_zep/pymacros/SiEPICfab_EBeam_ZEP_beta_fixed/ebeam_BondPad.gds
siepicfab_ebeam_zep/pymacros/SiEPICfab_EBeam_ZEP_beta_fixed/ebeam_GC_Air_te1550_BB.gds
siepicfab_ebeam_zep/pymacros/SiEPICfab_EBeam_ZEP_beta_fixed/ebeam_GC_Air_tm1310_BB.gds
siepicfab_ebeam_zep/pymacros/SiEPICfab_EBeam_ZEP_beta_fixed/ebeam_GC_Air_tm1550_BB.gds
siepicfab_ebeam_zep/pymacros/SiEPICfab_EBeam_ZEP_beta_fixed/ebeam_adiabatic_te1550.gds
siepicfab_ebeam_zep/pymacros/SiEPICfab_EBeam_ZEP_beta_fixed/ebeam_adiabatic_tm1550.gds
siepicfab_ebeam_zep/pymacros/SiEPICfab_EBeam_ZEP_beta_fixed/ebeam_crossing_te1310.gds
siepicfab_ebeam_zep/pymacros/SiEPICfab_EBeam_ZEP_beta_fixed/ebeam_crossing_te1550.gds
siepicfab_ebeam_zep/pymacros/SiEPICfab_EBeam_ZEP_beta_fixed/ebeam_directional_coupler_bdc_biasedP15nm_te1550.gds
siepicfab_ebeam_zep/pymacros/SiEPICfab_EBeam_ZEP_beta_fixed/ebeam_directional_coupler_bdc_te1550.GDS
siepicfab_ebeam_zep/pymacros/SiEPICfab_EBeam_ZEP_beta_fixed/ebeam_directional_coupler_bdc_te1550.gds
siepicfab_ebeam_zep-0.1.4.dist-info/LICENSE.md
siepicfab_ebeam_zep-0.1.4.dist-info/METADATA
siepicfab_ebeam_zep-0.1.4.dist-info/WHEEL
siepicfab_ebeam_zep-0.1.4.dist-info/top_level.txt
siepicfab_ebeam_zep-0.1.4.dist-info/RECORD
