Metadata-Version: 2.2
Name: siepicfab_ebeam_zep
Version: 0.1.4
Summary: SiEPICfab_EBeam_ZEP_PDK: process design kit (PDK) for fabrication using electron beam lithography, and a library silicon photonics components. 
Author-email: Lukas Chrostowski <lukasc@ece.ubc.ca>
Project-URL: Homepage, https://github.com/SiEPIC/SiEPICfab-EBeam-ZEP-PDK
Project-URL: Issues, https://github.com/SiEPIC/SiEPICfab-EBeam-ZEP-PDK/issues
Classifier: Programming Language :: Python :: 3
Classifier: License :: OSI Approved :: MIT License
Classifier: Operating System :: OS Independent
Requires-Python: >=3.8
License-File: LICENSE.md
Requires-Dist: SiEPIC>=0.5.20
Requires-Dist: numpy
Requires-Dist: packaging
